buks/__init__.py
buks/main.py
buks/models.py
buks-0.0.2.dist-info/METADATA
buks-0.0.2.dist-info/WHEEL
buks-0.0.2.dist-info/RECORD
